pytadata_entriz/__init__.py
pytadata_entriz/_detect.py
pytadata_entriz/_typing.py
pytadata_entriz/common/__init__.py
pytadata_entriz/common/base.py
pytadata_entriz/common/file_readers_gcp.py
pytadata_entriz/common/file_readers_local.py
pytadata_entriz/common/file_readers_s3.py
pytadata_entriz/common/helper.py
pytadata_entriz/common/logger.py
pytadata_entriz/common/object_factory.py
pytadata_entriz/common/validator.py
pytadata_entriz/data_entry.py
pytadata_entriz/providers/__init__.py
pytadata_entriz/providers/aws.py
pytadata_entriz/providers/gcp.py
pytadata_entriz/providers/local.py
pytadata_entriz-2.1.4.dist-info/METADATA
pytadata_entriz-2.1.4.dist-info/WHEEL
pytadata_entriz-2.1.4.dist-info/RECORD
