Metadata-Version: 2.3
Name: pytadata_entriz
Version: 2.1.4
Summary: Uniform DataFrame writer with optional AWS or GCP back-ends
License: MIT
Keywords: data-engineering,pandas,aws,gcp,bigquery,s3
Author: jaimeardp
Author-email: jaimeardp@gmail.com
Requires-Python: >=3.11,<4.0.0
Classifier: Development Status :: 4 - Beta
Classifier: Intended Audience :: Developers
Classifier: License :: OSI Approved :: MIT License
Classifier: Programming Language :: Python :: 3
Classifier: Programming Language :: Python :: 3.11
Classifier: Programming Language :: Python :: 3.12
Classifier: Topic :: Database
Classifier: Topic :: Software Development :: Libraries :: Python Modules
Provides-Extra: aws
Provides-Extra: dev
Provides-Extra: gcp
Requires-Dist: awswrangler (>=3.7,<4.0) ; extra == "aws"
Requires-Dist: black (>=24.0.0) ; extra == "dev"
Requires-Dist: flake8 (>=7.0.0) ; extra == "dev"
Requires-Dist: gcsfs (>=2024.3.0) ; extra == "gcp"
Requires-Dist: mypy (>=1.8.0) ; extra == "dev"
Requires-Dist: pandas (>=2.2,<3.0)
Requires-Dist: pandas-gbq (>=0.20,<1.0) ; extra == "gcp"
Requires-Dist: pyarrow (>=15.0,<16.0)
Requires-Dist: pytest (>=8.0.0) ; extra == "dev"
Requires-Dist: typedframe (>=0.11.0,<0.12.0)
Project-URL: Homepage, https://github.com/jaimeardp/pytadata_entriz
Project-URL: Issues, https://github.com/jaimeardp/pytadata_entriz.git/issues
Project-URL: Repository, https://github.com/jaimeardp/pytadata_entriz.git
